MANIFEST.in
setup.cfg
setup.py
tw2/__init__.py
tw2.qrcode.egg-info/PKG-INFO
tw2.qrcode.egg-info/SOURCES.txt
tw2.qrcode.egg-info/dependency_links.txt
tw2.qrcode.egg-info/entry_points.txt
tw2.qrcode.egg-info/namespace_packages.txt
tw2.qrcode.egg-info/not-zip-safe
tw2.qrcode.egg-info/requires.txt
tw2.qrcode.egg-info/top_level.txt
tw2/qrcode/__init__.py
tw2/qrcode/base.py
tw2/qrcode/samples.py
tw2/qrcode/widgets.py
tw2/qrcode/static/qrcode.css
tw2/qrcode/static/qrcode.js
tw2/qrcode/templates/__init__.py
tw2/qrcode/templates/__init__.pyc
tw2/qrcode/templates/qrcode.mak