Metadata-Version: 1.0
Name: tw2.qrcode
Version: 2.0.2
Summary: Client-side QR Code Widget
Home-page: http://github.com/gregjurman/tw2.qrcode
Author: Greg Jurman
Author-email: gdj2214@rit.edu
License: MIT
Keywords: toscawidgets.widgets,qrcode
Platform: UNKNOWN
Classifier: Development Status :: 3 - Alpha
Classifier: Environment :: Web Environment
Classifier: Environment :: Web Environment :: ToscaWidgets
Classifier: Topic :: Software Development :: Libraries :: Python Modules
Classifier: Topic :: Software Development :: Widget Sets
Classifier: Intended Audience :: Developers
Classifier: Operating System :: OS Independent
Classifier: Programming Language :: Python
